maybe/__init__.py
maybe/maybe.py
maybe/py.typed
rustedpy_maybe-0.0.0.dist-info/LICENSE
rustedpy_maybe-0.0.0.dist-info/METADATA
rustedpy_maybe-0.0.0.dist-info/WHEEL
rustedpy_maybe-0.0.0.dist-info/top_level.txt
rustedpy_maybe-0.0.0.dist-info/zip-safe
rustedpy_maybe-0.0.0.dist-info/RECORD
