Metadata-Version: 2.1
Name: rustedpy-maybe
Version: 0.0.0
Summary: A Rust-like option type for Python
Home-page: https://github.com/rustedpy/maybe
Author: francium
Author-email: francium@francium.cc
Maintainer: rustedpy github org members (https://github.com/rustedpy)
License: MIT
Keywords: rust,option,maybe,enum
Classifier: Development Status :: 4 - Beta
Classifier: License :: OSI Approved :: MIT License
Classifier: Programming Language :: Python :: 3
Classifier: Programming Language :: Python :: 3.8
Classifier: Programming Language :: Python :: 3.9
Classifier: Programming Language :: Python :: 3.10
Classifier: Programming Language :: Python :: 3.11
Classifier: Programming Language :: Python :: 3 :: Only
Requires-Python: >=3.8
License-File: LICENSE
Requires-Dist: typing-extensions ; python_version < "3.10"
